rocketscraper/__init__.py
rocketscraper/rocketscraper.py
rocketscraper-0.0.4.dist-info/LICENSE
rocketscraper-0.0.4.dist-info/METADATA
rocketscraper-0.0.4.dist-info/WHEEL
rocketscraper-0.0.4.dist-info/top_level.txt
rocketscraper-0.0.4.dist-info/RECORD
