Metadata-Version: 2.1
Name: rocketscraper
Version: 0.0.4
Summary: Python SDK for the Rocket Scraper API.
Author-email: Rocket Scraper API <support@rocketscraper.com>
License: MIT
Project-URL: Homepage, https://rocketscraper.com
Project-URL: Repository, https://github.com/rocketscraper/rocketscraper-sdk-python
Project-URL: Bug Tracker, https://github.com/rocketscraper/rocketscraper-sdk-python/issues
Keywords: rocketscraper,api,web-scraping,ai
Classifier: Programming Language :: Python :: 3
Classifier: License :: OSI Approved :: MIT License
Classifier: Operating System :: OS Independent
Requires-Python: >=3.7
License-File: LICENSE
